try_poetry/__init__.py
try_poetry/my_script.py
try_poetry-0.1.0.dist-info/WHEEL
try_poetry-0.1.0.dist-info/METADATA
try_poetry-0.1.0.dist-info/RECORD
